Metadata-Version: 1.0
Name: prob-distros-gausso-bino
Version: 0.1
Summary: Gaussian distributions and Binomial Distributions
Home-page: UNKNOWN
Author: Aneeket Deo
Author-email: aneeketdeo@gmail.com
License: UNKNOWN
Platform: UNKNOWN
